txtanalyze/__init__.py
txtanalyze/core.py
txtanalyze-1.0.1.dist-info/licenses/LICENSE
txtanalyze-1.0.1.dist-info/METADATA
txtanalyze-1.0.1.dist-info/WHEEL
txtanalyze-1.0.1.dist-info/top_level.txt
txtanalyze-1.0.1.dist-info/RECORD
