Metadata-Version: 2.4
Name: txtanalyze
Version: 1.0.1
Summary: A modular Python package for analyzing text paragraphs
Home-page: https://github.com/GH0STH4CKER/txtanalyze
Author: Dimuth Sakya
Author-email: Dimuth Sakya <dimuthsakya@protonmail.com>
License: MIT
Requires-Python: >=3.8
License-File: LICENSE
Dynamic: license-file
